{
	"info": {
		"_postman_id": "9c89ba4b-734a-45a7-8718-0967a2ff9470",
		"name": "Loftes",
		"description": "Pour le faire tourner, changez dans variable la valeur de bas_url\n",
		"schema": "https://schema.getpostman.com/json/collection/v2.1.0/collection.json"
	},
	"item": [
		{
			"name": "Challenges",
			"item": [
				{
					"name": "All challenges",
					"request": {
						"method": "GET",
						"header": [],
						"url": {
							"raw": "{{url_base}}/challenges",
							"host": [
								"{{url_base}}"
							],
							"path": [
								"challenges"
							]
						}
					},
					"response": []
				},
				{
					"name": "Challenge by id",
					"request": {
						"method": "GET",
						"header": [],
						"url": {
							"raw": "{{url_base}}/challenges/1",
							"host": [
								"{{url_base}}"
							],
							"path": [
								"challenges",
								"1"
							]
						}
					},
					"response": []
				},
				{
					"name": "Create challenge",
					"request": {
						"method": "POST",
						"header": [],
						"body": {
							"mode": "raw",
							"raw": "{\n\t\"name\":\"First Challenge\",\n\t\"description\":\"Description\", \n\t\"end_date\":\"2022-10-18\",\n    \"alone_only\" : 1,\n    \"level\" : \"Débutant\",\n    \"scalling\" : 10,\n    \"draft\": true,\n    \"start_crossing_point_id\" : 1,\n    \"end_crossing_point_id\" : 2,\n    \"admin_id\" : 1\n}",
							"options": {
								"raw": {
									"language": "json"
								}
							}
						},
						"url": {
							"raw": "{{url}}/challenges",
							"host": [
								"{{url}}"
							],
							"path": [
								"challenges"
							]
						}
					},
					"response": []
				},
				{
					"name": "Update challenge",
					"request": {
						"method": "PUT",
						"header": [],
						"body": {
							"mode": "raw",
							"raw": "{\n\t\"name\": \"Second name\", \n\t\"end_date\":\"2022-02-01\"\n}",
							"options": {
								"raw": {
									"language": "json"
								}
							}
						},
						"url": {
							"raw": "{{url_base}}/challenges/1",
							"host": [
								"{{url_base}}"
							],
							"path": [
								"challenges",
								"1"
							]
						}
					},
					"response": []
				},
				{
					"name": "Modify challenge",
					"request": {
						"method": "PATCH",
						"header": [],
						"body": {
							"mode": "raw",
							"raw": "{\n\t\"draft\":true\n}",
							"options": {
								"raw": {
									"language": "json"
								}
							}
						},
						"url": {
							"raw": "{{url_base}}/challenges/1",
							"host": [
								"{{url_base}}"
							],
							"path": [
								"challenges",
								"1"
							]
						}
					},
					"response": []
				},
				{
					"name": "Delete challenge",
					"request": {
						"method": "DELETE",
						"header": [],
						"url": {
							"raw": "{{url_base}}/challenges/1",
							"host": [
								"{{url_base}}"
							],
							"path": [
								"challenges",
								"1"
							]
						}
					},
					"response": []
				},
				{
					"name": "Download challenge's map",
					"request": {
						"method": "GET",
						"header": [],
						"url": {
							"raw": "{{url_base}}/challenges/1/image",
							"host": [
								"{{url_base}}"
							],
							"path": [
								"challenges",
								"1",
								"image"
							]
						}
					},
					"response": []
				},
				{
					"name": "Upload challenge's map",
					"request": {
						"method": "POST",
						"header": [],
						"body": {
							"mode": "formdata",
							"formdata": [
								{
									"key": "file",
									"type": "file",
									"src": []
								}
							]
						},
						"url": {
							"raw": "{{url_base}}/challenges/1/image",
							"host": [
								"{{url_base}}"
							],
							"path": [
								"challenges",
								"1",
								"image"
							]
						}
					},
					"response": []
				},
				{
					"name": "ChallengeSubscribe",
					"request": {
						"auth": {
							"type": "bearer",
							"bearer": [
								{
									"key": "token",
									"value": "eyJ0eXAiOiJKV1QiLCJhbGciOiJIUzUxMiJ9.eyJzdWIiOiJsZW1haXRyZUBnbWFpbC5jb20iLCJpYXQiOjE2MTkwNDkyMjcsImV4cCI6MTYxOTA1MjgyN30.vAQ1IMG4UkOwwPIe9Pd6GoE0cwVd42XkmS3ByrkSEBbkYxFTyoyMusO1zj1k6H7L0k5koWFvdFoHJtVrBl8mDA",
									"type": "string"
								}
							]
						},
						"method": "POST",
						"header": [],
						"url": {
							"raw": "{{url_base}}/challenges/1/subscribe",
							"host": [
								"{{url_base}}"
							],
							"path": [
								"challenges",
								"1",
								"subscribe"
							]
						}
					},
					"response": []
				},
				{
					"name": "ChallengeUnsubscribe",
					"request": {
						"auth": {
							"type": "bearer",
							"bearer": [
								{
									"key": "token",
									"value": "eyJ0eXAiOiJKV1QiLCJhbGciOiJIUzUxMiJ9.eyJzdWIiOiJhbGFiaWNuQGhvdG1haWwuY29tIiwiaWF0IjoxNjE5NDcwMjE3LCJleHAiOjE2MTk0NzM4MTd9.U964gWZXH38CuNbB3UOszz4BSTFsr_uwzx_xq1Fgwd1pL9NqSIuWI-RkngstDb1uM81vwm2eLt8jJHVBVryufA",
									"type": "string"
								}
							]
						},
						"method": "POST",
						"header": [],
						"url": {
							"raw": "{{url_base}}/challenges/1/unsubscribe",
							"host": [
								"{{url_base}}"
							],
							"path": [
								"challenges",
								"1",
								"unsubscribe"
							]
						}
					},
					"response": []
				},
				{
					"name": "ChallengeVerify",
					"request": {
						"auth": {
							"type": "bearer",
							"bearer": [
								{
									"key": "token",
									"value": "eyJ0eXAiOiJKV1QiLCJhbGciOiJIUzUxMiJ9.eyJzdWIiOiJsZW1haXRyZUBnbWFpbC5jb20iLCJpYXQiOjE2MjAwMjQ4NjIsImV4cCI6MTYyMDAyODQ2Mn0.S1F0N-hEdRdfhH1ElL6JxRNbheauYd1w1vb_lygmiwPdU5cyUD_5ooHumJOoTSamnWoaePPlvwahz4TxUihdww",
									"type": "string"
								}
							]
						},
						"method": "POST",
						"header": [],
						"url": {
							"raw": "{{url_base}}/challenges/:id/verify",
							"host": [
								"{{url_base}}"
							],
							"path": [
								"challenges",
								":id",
								"verify"
							],
							"variable": [
								{
									"key": "id",
									"value": "1"
								}
							]
						}
					},
					"response": []
				}
			],
			"description": "Requête pour un challenge\n\nDonnées envoyé dans le JSON sous forme de body \n\nChamps obligatoire en création\n - name\n\nChamps utilisable en modification : \n - name\n - description \n - end_date = \tForamt \"YYYY-MM-DD\"\n -  alone_only = 0 ou 1\n - leve\" : Niveau du challenge,\n - scalling\" : niveau\n - draft : true ou false\n - start_crossing_point_id : id du crossing point\n - end_crossing_point_id : id du crossing point\n - admin_id : id de l'administrateur\n\n\n  Exemple pour modification\n    {\n        \"name\":\"First Challenge\",\n        \"description\":\"Description\", \n        \"end_date\":\"2022-10-18\",\n        \"alone_only\" : 1,\n        \"level\" : \"Débutant\",\n        \"scalling\" : 10,\n        \"draft\": true,\n        \"start_crossing_point_id\" : 1,\n        \"end_crossing_point_id\" : 2,\n        \"admin_id\" : 1\n    }",
			"event": [
				{
					"listen": "prerequest",
					"script": {
						"type": "text/javascript",
						"exec": [
							""
						],
						"id": "979037c7-b29d-4aab-8cda-11a8329be992"
					}
				},
				{
					"listen": "test",
					"script": {
						"type": "text/javascript",
						"exec": [
							""
						],
						"id": "d5957aa1-130e-45d6-965f-3c48d34e3073"
					}
				}
			],
			"protocolProfileBehavior": {}
		},
		{
			"name": "Segments",
			"item": [
				{
					"name": "SEGMENT_ALL",
					"event": [
						{
							"listen": "test",
							"script": {
								"exec": [
									""
								],
								"type": "text/javascript",
								"id": "9830439c-5c16-4a32-8ca6-82f712f55eae"
							}
						}
					],
					"protocolProfileBehavior": {
						"disableBodyPruning": true
					},
					"request": {
						"method": "GET",
						"header": [],
						"body": {
							"mode": "raw",
							"raw": "",
							"options": {
								"raw": {
									"language": "json"
								}
							}
						},
						"url": {
							"raw": "{{url_base}}/challenges/1/segments",
							"host": [
								"{{url_base}}"
							],
							"path": [
								"challenges",
								"1",
								"segments"
							]
						}
					},
					"response": []
				},
				{
					"name": "SEGMENT_FIND_BY_ID",
					"event": [
						{
							"listen": "test",
							"script": {
								"exec": [
									""
								],
								"type": "text/javascript",
								"id": "5b25a4e2-40ec-4b6f-b6f0-f370aa970e38"
							}
						}
					],
					"protocolProfileBehavior": {
						"disableBodyPruning": true
					},
					"request": {
						"method": "GET",
						"header": [],
						"body": {
							"mode": "raw",
							"raw": "",
							"options": {
								"raw": {
									"language": "json"
								}
							}
						},
						"url": {
							"raw": "{{url_base}}/challenges/1/segments/2",
							"host": [
								"{{url_base}}"
							],
							"path": [
								"challenges",
								"1",
								"segments",
								"2"
							]
						}
					},
					"response": []
				},
				{
					"name": "SEGMENT_ADD",
					"event": [
						{
							"listen": "test",
							"script": {
								"exec": [
									""
								],
								"type": "text/javascript",
								"id": "5f8eaf38-464d-48e1-a188-a0559b87f4db"
							}
						}
					],
					"request": {
						"method": "POST",
						"header": [],
						"body": {
							"mode": "raw",
							"raw": "{\n    \"name\" : \"Mon segment\",\n    \"start_crossing_point_id\" : \"2\",\n    \"end_crossing_point_id\" : \"4\",\n    \"list_points\"  : \"(('0.1','0.2'),('0.1','0.2'),('0.1','0.2'))\"\n}",
							"options": {
								"raw": {
									"language": "json"
								}
							}
						},
						"url": {
							"raw": "{{url_base}}/challenges/1/segments",
							"host": [
								"{{url_base}}"
							],
							"path": [
								"challenges",
								"1",
								"segments"
							]
						}
					},
					"response": []
				},
				{
					"name": "SEGMENT_UPDATE",
					"event": [
						{
							"listen": "test",
							"script": {
								"exec": [
									""
								],
								"type": "text/javascript",
								"id": "fbe41ff6-ef08-419d-8b82-80c81f3a4c7e"
							}
						}
					],
					"request": {
						"method": "PUT",
						"header": [],
						"body": {
							"mode": "raw",
							"raw": "{\n     \"name\" : \"Mon segment 3\" \n}",
							"options": {
								"raw": {
									"language": "json"
								}
							}
						},
						"url": {
							"raw": "{{url_base}}/challenges/1/segments/5",
							"host": [
								"{{url_base}}"
							],
							"path": [
								"challenges",
								"1",
								"segments",
								"5"
							]
						}
					},
					"response": []
				},
				{
					"name": "SEGMENT_MODIFY",
					"event": [
						{
							"listen": "test",
							"script": {
								"exec": [
									""
								],
								"type": "text/javascript",
								"id": "3ad27348-737c-4201-b367-bba2780ae06f"
							}
						}
					],
					"request": {
						"method": "PATCH",
						"header": [],
						"body": {
							"mode": "raw",
							"raw": "{\n    \n   \"start_crossing_point_id\" : \"3\"\n}",
							"options": {
								"raw": {
									"language": "json"
								}
							}
						},
						"url": {
							"raw": "{{url_base}}/challenges/2/segments/5",
							"host": [
								"{{url_base}}"
							],
							"path": [
								"challenges",
								"2",
								"segments",
								"5"
							]
						}
					},
					"response": []
				},
				{
					"name": "SEGMENT_DELETE",
					"event": [
						{
							"listen": "test",
							"script": {
								"exec": [
									""
								],
								"type": "text/javascript",
								"id": "03743e4c-59e9-472b-acc9-7b7a738472bb"
							}
						}
					],
					"request": {
						"method": "DELETE",
						"header": [],
						"body": {
							"mode": "raw",
							"raw": "",
							"options": {
								"raw": {
									"language": "json"
								}
							}
						},
						"url": {
							"raw": "{{url_base}}/challenges/2/segments/5",
							"host": [
								"{{url_base}}"
							],
							"path": [
								"challenges",
								"2",
								"segments",
								"5"
							]
						}
					},
					"response": []
				}
			],
			"protocolProfileBehavior": {}
		},
		{
			"name": "CrossingPoint",
			"item": [
				{
					"name": "CROSSING_POINT_ALL",
					"event": [
						{
							"listen": "test",
							"script": {
								"exec": [
									""
								],
								"type": "text/javascript",
								"id": "1c6a7cac-58ef-4a8a-a017-84af19a58572"
							}
						}
					],
					"protocolProfileBehavior": {
						"disableBodyPruning": true
					},
					"request": {
						"method": "GET",
						"header": [],
						"body": {
							"mode": "raw",
							"raw": "",
							"options": {
								"raw": {
									"language": "json"
								}
							}
						},
						"url": {
							"raw": "{{url_base}}/challenges/1/crossing-points",
							"host": [
								"{{url_base}}"
							],
							"path": [
								"challenges",
								"1",
								"crossing-points"
							]
						},
						"description": "You can use /crossingpoints to get all the crossing in the database"
					},
					"response": []
				},
				{
					"name": "CROSSING_POINT_FIND_BY_ID",
					"event": [
						{
							"listen": "test",
							"script": {
								"exec": [
									""
								],
								"type": "text/javascript",
								"id": "b8df7223-2cc7-464e-a41d-bae56cb3457c"
							}
						}
					],
					"protocolProfileBehavior": {
						"disableBodyPruning": true
					},
					"request": {
						"method": "GET",
						"header": [],
						"body": {
							"mode": "raw",
							"raw": "",
							"options": {
								"raw": {
									"language": "json"
								}
							}
						},
						"url": {
							"raw": "{{url_base}}/challenges/1/crossing-points/1",
							"host": [
								"{{url_base}}"
							],
							"path": [
								"challenges",
								"1",
								"crossing-points",
								"1"
							]
						}
					},
					"response": []
				},
				{
					"name": "CROSSING_POINT_ADD",
					"event": [
						{
							"listen": "test",
							"script": {
								"exec": [
									""
								],
								"type": "text/javascript",
								"id": "1f7ef305-f752-4634-819d-e937a3b55c36"
							}
						}
					],
					"request": {
						"method": "POST",
						"header": [],
						"body": {
							"mode": "raw",
							"raw": "{\n    \"name\":\"La maison de Monsieur Tumnus 2\",\n    \"position_x\":\"0.42\",\n    \"position_y\":\"0.45\"\n}",
							"options": {
								"raw": {
									"language": "json"
								}
							}
						},
						"url": {
							"raw": "{{url_base}}/challenges/1/crossing-points",
							"host": [
								"{{url_base}}"
							],
							"path": [
								"challenges",
								"1",
								"crossing-points"
							],
							"query": [
								{
									"key": "",
									"value": "",
									"disabled": true
								},
								{
									"key": "",
									"value": "",
									"disabled": true
								},
								{
									"key": "",
									"value": "",
									"disabled": true
								},
								{
									"key": "",
									"value": "",
									"disabled": true
								},
								{
									"key": "",
									"value": "",
									"disabled": true
								}
							]
						},
						"description": "## Create a crossing point\n\nUse to create a crossing point \nThe data were pass throught thte request body\n\n### Mandatory fields\n\n* name_crossing : the name of the crossing point\n* challenge_id  : The ide of the challenge\n* x_position    : The x position on the map\n* y_position    : The y position on the map\n\n### Example\n\n`{  \n   \"name_crossing\":\"Mos Eisley 3\",   \"challenge_id\" : \"2\",  \n   \"x_position\":\"0.20\",    \n   \"y_position\":\"0.40\"      \n}`\n\n### Result"
					},
					"response": []
				},
				{
					"name": "CROSSING_UPDATE_BY_ID",
					"event": [
						{
							"listen": "test",
							"script": {
								"exec": [
									""
								],
								"type": "text/javascript",
								"id": "ce536068-1577-4b23-ab00-970ba9d83f94"
							}
						}
					],
					"request": {
						"method": "PUT",
						"header": [],
						"body": {
							"mode": "raw",
							"raw": "{\n    \"name\":\"La maison de Monsieur Tumnus\"\n}",
							"options": {
								"raw": {
									"language": "json"
								}
							}
						},
						"url": {
							"raw": "{{url_base}}/challenges/1/crossing-points/10",
							"host": [
								"{{url_base}}"
							],
							"path": [
								"challenges",
								"1",
								"crossing-points",
								"10"
							]
						}
					},
					"response": []
				},
				{
					"name": "CROSSING_MODIFY",
					"event": [
						{
							"listen": "test",
							"script": {
								"exec": [
									""
								],
								"type": "text/javascript",
								"id": "0f66010e-f1f7-4db0-b210-183cfb57bce9"
							}
						}
					],
					"request": {
						"method": "PATCH",
						"header": [],
						"body": {
							"mode": "raw",
							"raw": "{\n    \"name\":\"La maison de Monsieur Tumnus 2\"\n}",
							"options": {
								"raw": {
									"language": "json"
								}
							}
						},
						"url": {
							"raw": "{{url_base}}/challenges/1/crossing-points/11",
							"host": [
								"{{url_base}}"
							],
							"path": [
								"challenges",
								"1",
								"crossing-points",
								"11"
							]
						}
					},
					"response": []
				},
				{
					"name": "CROSSING_POINT_DELETE",
					"event": [
						{
							"listen": "test",
							"script": {
								"exec": [
									""
								],
								"type": "text/javascript",
								"id": "065811e5-4b6b-4d44-8061-67af34ee8aaf"
							}
						}
					],
					"request": {
						"method": "DELETE",
						"header": [],
						"body": {
							"mode": "raw",
							"raw": "",
							"options": {
								"raw": {
									"language": "json"
								}
							}
						},
						"url": {
							"raw": "{{url_base}}/challenges/1/crossing-points/11",
							"host": [
								"{{url_base}}"
							],
							"path": [
								"challenges",
								"1",
								"crossing-points",
								"11"
							]
						}
					},
					"response": []
				}
			],
			"protocolProfileBehavior": {}
		},
		{
			"name": "Events",
			"item": [
				{
					"name": "EVENTS_ALL",
					"event": [
						{
							"listen": "test",
							"script": {
								"exec": [
									""
								],
								"type": "text/javascript",
								"id": "942d6fa3-4070-43d7-9b9c-9d1a08a1f0dc"
							}
						}
					],
					"protocolProfileBehavior": {
						"disableBodyPruning": true
					},
					"request": {
						"method": "GET",
						"header": [],
						"body": {
							"mode": "raw",
							"raw": "",
							"options": {
								"raw": {
									"language": "json"
								}
							}
						},
						"url": {
							"raw": "{{url_base}}/challenges/1/events",
							"host": [
								"{{url_base}}"
							],
							"path": [
								"challenges",
								"1",
								"events"
							]
						}
					},
					"response": []
				},
				{
					"name": "EVENT_FIND_BY_ID",
					"event": [
						{
							"listen": "test",
							"script": {
								"id": "67d717ae-488e-4b8b-a087-68b8e8522619",
								"exec": [
									""
								],
								"type": "text/javascript"
							}
						}
					],
					"protocolProfileBehavior": {
						"disableBodyPruning": true
					},
					"request": {
						"method": "GET",
						"header": [],
						"body": {
							"mode": "raw",
							"raw": "",
							"options": {
								"raw": {
									"language": "json"
								}
							}
						},
						"url": {
							"raw": "{{url_base}}/challenges/1/segments/1/events/19",
							"host": [
								"{{url_base}}"
							],
							"path": [
								"challenges",
								"1",
								"segments",
								"1",
								"events",
								"19"
							]
						}
					},
					"response": []
				},
				{
					"name": "EVENT_ADD",
					"event": [
						{
							"listen": "test",
							"script": {
								"id": "62b1336b-1329-44c8-9666-24b9edd3bd3c",
								"exec": [
									""
								],
								"type": "text/javascript"
							}
						}
					],
					"request": {
						"method": "POST",
						"header": [
							{
								"key": "token",
								"value": "1",
								"type": "text"
							}
						],
						"body": {
							"mode": "raw",
							"raw": "{\n    \"move_type\": 3,\n    \"event_type_id\": 1,\n    \"event_date\":\"2021-04-02 12:55:34\",\n    \"distance\":350,\n    \"duration\": 5400\n}",
							"options": {
								"raw": {
									"language": "json"
								}
							}
						},
						"url": {
							"raw": "{{url_base}}/challenges/1/segments/1/events",
							"host": [
								"{{url_base}}"
							],
							"path": [
								"challenges",
								"1",
								"segments",
								"1",
								"events"
							],
							"query": [
								{
									"key": "",
									"value": "",
									"disabled": true
								},
								{
									"key": "",
									"value": "",
									"disabled": true
								},
								{
									"key": "",
									"value": "",
									"disabled": true
								},
								{
									"key": "",
									"value": "",
									"disabled": true
								},
								{
									"key": "",
									"value": "",
									"disabled": true
								}
							]
						}
					},
					"response": []
				},
				{
					"name": "EVENT_CHECK_RESPONSE",
					"event": [
						{
							"listen": "test",
							"script": {
								"id": "a8b911d6-1726-43de-b89e-919be457dc14",
								"exec": [
									""
								],
								"type": "text/javascript"
							}
						}
					],
					"request": {
						"method": "POST",
						"header": [],
						"body": {
							"mode": "raw",
							"raw": "{\n    \"event_type_id\": 5,\n    \"event_date\":\"2022-10-18 15:00:00\",\n    \"obstacle_id\":2,\n    \"response\": \"L'empereur d'au-delà des Mer\"\n}",
							"options": {
								"raw": {
									"language": "json"
								}
							}
						},
						"url": {
							"raw": "{{url_base}}/challenges/1/segments/1/events/checkresponse",
							"host": [
								"{{url_base}}"
							],
							"path": [
								"challenges",
								"1",
								"segments",
								"1",
								"events",
								"checkresponse"
							]
						}
					},
					"response": []
				}
			],
			"protocolProfileBehavior": {}
		},
		{
			"name": "EventsType",
			"item": [
				{
					"name": "EVENT_TYPES_ADD",
					"event": [
						{
							"listen": "test",
							"script": {
								"exec": [
									""
								],
								"type": "text/javascript",
								"id": "d19d65b7-5840-4c62-b41e-7baa13fbdb19"
							}
						}
					],
					"request": {
						"method": "POST",
						"header": [],
						"body": {
							"mode": "raw",
							"raw": "{\n    \"code\":\"TEST 3\",\n    \"label\":\"test label 3\"\n}",
							"options": {
								"raw": {
									"language": "json"
								}
							}
						},
						"url": {
							"raw": "{{url_base}}/event-type",
							"host": [
								"{{url_base}}"
							],
							"path": [
								"event-type"
							]
						}
					},
					"response": []
				},
				{
					"name": "EVENT_TYPES_ALL",
					"event": [
						{
							"listen": "test",
							"script": {
								"exec": [
									""
								],
								"type": "text/javascript",
								"id": "16f054fc-4521-442a-9066-7ad9138aeffc"
							}
						}
					],
					"protocolProfileBehavior": {
						"disableBodyPruning": true
					},
					"request": {
						"method": "GET",
						"header": [],
						"body": {
							"mode": "raw",
							"raw": "",
							"options": {
								"raw": {
									"language": "json"
								}
							}
						},
						"url": {
							"raw": "{{url_base}}/event-type",
							"host": [
								"{{url_base}}"
							],
							"path": [
								"event-type"
							]
						}
					},
					"response": []
				},
				{
					"name": "EVENT_TYPES_FIND",
					"event": [
						{
							"listen": "test",
							"script": {
								"exec": [
									""
								],
								"type": "text/javascript",
								"id": "9ee5992c-e6a5-40fe-ab7b-5546b6bf5bd4"
							}
						}
					],
					"protocolProfileBehavior": {
						"disableBodyPruning": true
					},
					"request": {
						"method": "GET",
						"header": [],
						"body": {
							"mode": "raw",
							"raw": "{\n    \"code\":\"TEST 2\",\n    \"label\":\"test label 2\"\n}",
							"options": {
								"raw": {
									"language": "json"
								}
							}
						},
						"url": {
							"raw": "{{url_base}}/event-type/3",
							"host": [
								"{{url_base}}"
							],
							"path": [
								"event-type",
								"3"
							]
						}
					},
					"response": []
				}
			],
			"protocolProfileBehavior": {}
		},
		{
			"name": "Obstacles",
			"item": [
				{
					"name": "OBSTACLES_ALL",
					"event": [
						{
							"listen": "test",
							"script": {
								"id": "4895d14b-2ed9-4be0-9008-eb584aa5fe24",
								"exec": [
									""
								],
								"type": "text/javascript",
								"id": "4895d14b-2ed9-4be0-9008-eb584aa5fe24"
							}
						}
					],
					"protocolProfileBehavior": {
						"disableBodyPruning": true
					},
					"request": {
						"method": "GET",
						"header": [],
						"body": {
							"mode": "raw",
							"raw": "",
							"options": {
								"raw": {
									"language": "json"
								}
							}
						},
						"url": {
							"raw": "{{url_base}}/challenges/1/obstacles",
							"host": [
								"{{url_base}}"
							],
							"path": [
								"challenges",
								"1",
								"obstacles"
							]
						}
					},
					"response": []
				},
				{
					"name": "OBSTACLES_ADD",
					"event": [
						{
							"listen": "test",
							"script": {
								"id": "8e60d7d1-e9a8-4730-95c9-7c6acd27bb0e",
								"exec": [
									""
								],
								"type": "text/javascript"
							}
						}
					],
					"request": {
						"method": "POST",
						"header": [],
						"body": {
							"mode": "raw",
							"raw": "{\n    \"label\": \"Qui est le père d'Aslan 2 ?\",\n    \"progress\": 50,\n    \"description\": \"\",\n    \"type_question\": 0,\n    \"nb_point\": 25,\n    \"result\": \"L'empereur d'au-delà des Mers\"\n}",
							"options": {
								"raw": {
									"language": "json"
								}
							}
						},
						"url": {
							"raw": "{{url_base}}/challenges/1/segments/7/obstacles",
							"host": [
								"{{url_base}}"
							],
							"path": [
								"challenges",
								"1",
								"segments",
								"7",
								"obstacles"
							]
						}
					},
					"response": []
				},
				{
					"name": "OBSTACLES_FIND_BY_ID",
					"event": [
						{
							"listen": "test",
							"script": {
								"id": "8d3742ec-afb1-48a1-b767-bccd1ee4b696",
								"exec": [
									""
								],
								"type": "text/javascript",
								"id": "e4ea9129-ac01-4fd2-9a15-11fa85f6a652"
							}
						}
					],
					"protocolProfileBehavior": {
						"disableBodyPruning": true
					},
					"request": {
						"method": "GET",
						"header": [],
						"body": {
							"mode": "raw",
							"raw": "",
							"options": {
								"raw": {
									"language": "json"
								}
							}
						},
						"url": {
							"raw": "{{url_base}}/challenges/1/segments/1/obstacles/2",
							"host": [
								"{{url_base}}"
							],
							"path": [
								"challenges",
								"1",
								"segments",
								"1",
								"obstacles",
								"2"
							]
						}
					},
					"response": []
				},
				{
					"name": "OBSTACLES_UPDATE",
					"event": [
						{
							"listen": "test",
							"script": {
								"exec": [
									""
								],
								"type": "text/javascript",
								"id": "97b37a04-f965-49fa-be82-e8017827497c"
							}
						}
					],
					"request": {
						"method": "PUT",
						"header": [],
						"body": {
							"mode": "raw",
							"raw": "{\n    \"libelle\": \"Qui offre des armes aux enfants Pevensie ?\",\n    \"progress\": 70,\n    \"description\": \"\",\n    \"type_question\": 0,\n    \"nb_point\": 25,\n    \"result\": \"Le père Noel\"\n}",
							"options": {
								"raw": {
									"language": "json"
								}
							}
						},
						"url": {
							"raw": "{{url_base}}/challenges/1/segments/1/obstacles/6",
							"host": [
								"{{url_base}}"
							],
							"path": [
								"challenges",
								"1",
								"segments",
								"1",
								"obstacles",
								"6"
							]
						}
					},
					"response": []
				},
				{
					"name": "OBSTACLES_MODIFY",
					"event": [
						{
							"listen": "test",
							"script": {
								"exec": [
									""
								],
								"type": "text/javascript",
								"id": "a8b911d6-1726-43de-b89e-919be457dc14"
							}
						}
					],
					"request": {
						"method": "PATCH",
						"header": [],
						"body": {
							"mode": "raw",
							"raw": "{\n    \"libelle\": \"Qui Susan Pevensie, rencontre en premier à Narnia ?\",\n    \"result\": \"Mr Tumnus2\",\n    \"segment_id\":1\n}",
							"options": {
								"raw": {
									"language": "json"
								}
							}
						},
						"url": {
							"raw": "{{url_base}}/challenges/1/segments/1/obstacles/5",
							"host": [
								"{{url_base}}"
							],
							"path": [
								"challenges",
								"1",
								"segments",
								"1",
								"obstacles",
								"5"
							]
						}
					},
					"response": []
				},
				{
					"name": "OBSTACLES_DELETE",
					"event": [
						{
							"listen": "test",
							"script": {
								"exec": [
									""
								],
								"type": "text/javascript",
								"id": "b0fe2ed2-5e3b-4e42-99af-418c303bb660"
							}
						}
					],
					"request": {
						"method": "DELETE",
						"header": [],
						"body": {
							"mode": "raw",
							"raw": "",
							"options": {
								"raw": {
									"language": "json"
								}
							}
						},
						"url": {
							"raw": "{{url_base}}/challenges/1/segments/1/obstacles/10",
							"host": [
								"{{url_base}}"
							],
							"path": [
								"challenges",
								"1",
								"segments",
								"1",
								"obstacles",
								"10"
							]
						}
					},
					"response": []
				}
			],
			"protocolProfileBehavior": {}
		},
		{
			"name": "Authentication",
			"item": [
				{
					"name": "New Request",
					"request": {
						"method": "POST",
						"header": [],
						"body": {
							"mode": "raw",
							"raw": "{\n\t\"first_name\":\"Harry\", \n\t\"last_name\":\"Potter\", \n\t\"pseudo\":\"h_potter\", \n\t\"email\":\"potter@hotmail.com\", \n\t\"password\":\"hogwarts\"\n}",
							"options": {
								"raw": {
									"language": "json"
								}
							}
						},
						"url": {
							"raw": "{{url_base}}/signup",
							"host": [
								"{{url_base}}"
							],
							"path": [
								"signup"
							]
						}
					},
					"response": []
				},
				{
					"name": "New Request",
					"request": {
						"method": "POST",
						"header": [],
						"body": {
							"mode": "raw",
							"raw": "{\n\t\"email\":\"lemaitre@gmail.com\", \n\t\"password\":\"Conquérantdelunivers\"\n}",
							"options": {
								"raw": {
									"language": "json"
								}
							}
						},
						"url": {
							"raw": "{{url_base}}/login",
							"host": [
								"{{url_base}}"
							],
							"path": [
								"login"
							]
						}
					},
					"response": []
				},
				{
					"name": "New Request",
					"request": {
						"method": "GET",
						"header": [],
						"url": {
							"raw": ""
						}
					},
					"response": []
				}
			],
			"protocolProfileBehavior": {}
		}
	],
	"event": [
		{
			"listen": "prerequest",
			"script": {
				"type": "text/javascript",
				"exec": [
					""
				],
				"id": "d4ec0904-43b7-4ad3-8a28-f179930e9f18"
			}
		},
		{
			"listen": "test",
			"script": {
				"type": "text/javascript",
				"exec": [
					""
				],
				"id": "c4918abb-b5f3-4f74-8da9-94059a9c60cf"
			}
		}
	],
	"variable": [
		{
			"id": "234b7570-33ac-4fc8-a35f-eac93f20e289",
			"key": "url_base",
			"value": "http://localhost:6543"
		}
	],
	"protocolProfileBehavior": {}
}